geoserver/__init__.py
geoserver/base.py
geoserver/consts.py
geoserver/exceptions.py
geoserver/geoserver.py
geoserver/geowebcache.py
geoserver/utils.py
geoserver_py-0.2.0.dist-info/LICENSE
geoserver_py-0.2.0.dist-info/METADATA
geoserver_py-0.2.0.dist-info/WHEEL
geoserver_py-0.2.0.dist-info/RECORD
