Metadata-Version: 2.1
Name: geoserver-py
Version: 0.2.0
Summary: Minimal python client to communicate with Geoserver.
Home-page: https://github.com/arthurdjn/geoserver-py/
License: MIT
Keywords: geoserver,python,client,api
Author: Arthur Dujardin
Author-email: arthurdujardin.github@gmail.com
Maintainer: Arthur Dujardin
Maintainer-email: arthurdujardin.github@gmail.com
Requires-Python: >=3.9,<4.0
Classifier: License :: OSI Approved :: MIT License
Classifier: Operating System :: OS Independent
Classifier: Programming Language :: Python :: 3
Classifier: Programming Language :: Python :: 3.9
Classifier: Programming Language :: Python :: 3.10
Classifier: Programming Language :: Python :: 3.11
Classifier: Programming Language :: Python :: 3.12
Requires-Dist: requests (>=2.31.0,<3.0.0)
Requires-Dist: typing-extensions (>=4.12.1,<5.0.0)
Project-URL: Documentation, https://github.com/arthurdjn/geoserver-py/
Project-URL: Repository, https://github.com/arthurdjn/geoserver-py/
